{"flightmaster":null,"innkeeper":null,"repair":[{"coords":[[47.6,75.8]],"level":0,"name":"Elle Arcspark","type":1,"id":218747,"reacthorde":1,"reactalliance":1,"description":"Engineering Supplies"},{"coords":[[47.2,75.8]],"level":0,"name":"Clink Coppernozzle","type":1,"id":219976,"reacthorde":1,"reactalliance":1,"description":"Armor Vendor"}],"vendor":[{"coords":[[47.0,75.4]],"level":0,"name":"Apprentice Darius","type":1,"id":18255,"reacthorde":1,"reactalliance":1,"description":null},{"coords":[[47.6,75.8]],"level":0,"name":"Elle Arcspark","type":1,"id":218747,"reacthorde":1,"reactalliance":1,"description":"Engineering Supplies"},{"coords":[[47.2,75.8]],"level":0,"name":"Clink Coppernozzle","type":1,"id":219976,"reacthorde":1,"reactalliance":1,"description":"Armor Vendor"}],"trainer":null,"herb":null,"vein":null,"skinnable":[],"gatherable":[],"minable":[],"salvegable":[]}