{"flightmaster":[{"coords":[[56.2,31.0]],"level":0,"name":"Swift Seahorse","type":1,"id":40852,"reacthorde":1,"reactalliance":1,"description":"Flight Master"},{"coords":[[49.2,87.8]],"level":0,"name":"Swift Seahorse","type":1,"id":43216,"reacthorde":1,"reactalliance":-1,"description":"Flight Master"},{"coords":[[42.4,66.2]],"level":0,"name":"Swift Seahorse","type":1,"id":43287,"reacthorde":-1,"reactalliance":1,"description":"Flight Master"}],"innkeeper":[{"coords":[[45.0,23.2]],"level":0,"name":"Erunak Stonespeaker","type":1,"id":36915,"reacthorde":0,"reactalliance":1,"description":"The Earthen Ring"},{"coords":[[63.8,59.8]],"level":0,"name":"Erunak Stonespeaker","type":1,"id":41341,"reacthorde":1,"reactalliance":1,"description":"The Earthen Ring"},{"coords":[[38.8,31.6]],"level":0,"name":"Erunak Stonespeaker","type":1,"id":41618,"reacthorde":1,"reactalliance":0,"description":"The Earthen Ring"}],"repair":[{"coords":[[57.2,28.8]],"level":0,"name":"Captain Samir","type":1,"id":39884,"reacthorde":1,"reactalliance":1,"description":"Blacksmith"},{"coords":[[38.8,31.4]],"level":0,"name":"Rusty Anvil","type":1,"id":41461,"reacthorde":1,"reactalliance":1,"description":null}],"vendor":[{"coords":[[45.0,23.2]],"level":0,"name":"Erunak Stonespeaker","type":1,"id":36915,"reacthorde":0,"reactalliance":1,"description":"The Earthen Ring"},{"coords":[[57.2,28.8]],"level":0,"name":"Captain Samir","type":1,"id":39884,"reacthorde":1,"reactalliance":1,"description":"Blacksmith"},{"coords":[[63.8,59.8]],"level":0,"name":"Erunak Stonespeaker","type":1,"id":41341,"reacthorde":1,"reactalliance":1,"description":"The Earthen Ring"},{"coords":[[38.8,31.2]],"level":0,"name":"Salvaged Goods","type":1,"id":41508,"reacthorde":1,"reactalliance":1,"description":null},{"coords":[[38.8,31.6]],"level":0,"name":"Erunak Stonespeaker","type":1,"id":41618,"reacthorde":1,"reactalliance":0,"description":"The Earthen Ring"},{"coords":[[60.4,58.6]],"level":0,"name":"Ol' Fishbreath","type":1,"id":132562,"reacthorde":1,"reactalliance":1,"description":null}],"trainer":null,"herb":{"Stormvine":[{"coords":[[46.2,21.8],[46.9,46.4],[46.9,46.5],[47.7,21.1],[48.4,47.7],[48.5,47.8],[49.0,44.4],[49.0,44.5],[49.4,22.0],[49.6,22.0],[50.4,19.4],[50.4,19.6],[50.5,19.4],[50.5,19.6],[51.1,47.2],[51.1,47.5],[54.3,56.4],[54.3,56.7],[54.5,56.7],[55.3,54.6],[55.4,54.4],[55.5,54.4],[55.5,54.6],[55.9,68.8],[56.1,66.8],[56.9,52.4],[56.9,52.5],[57.0,76.4],[57.0,76.6],[57.8,55.4],[57.8,55.5],[58.2,69.8],[58.4,64.4],[58.4,64.7],[58.4,72.4],[58.4,72.5],[58.5,64.7],[58.5,72.4],[58.5,72.5],[58.6,64.4],[59.0,77.7],[59.7,73.8],[62.7,4.5],[65.1,8.8],[65.5,16.9],[65.6,15.8],[66.1,21.4],[67.0,14.6],[67.3,22.1],[67.7,19.9],[76.8,37.8]],"level":0,"name":"Stormvine","type":2,"id":202748}],"Azshara's Veil":[{"coords":[[35.3,58.6],[39.4,21.0],[39.5,21.0],[39.7,19.0],[40.3,17.1],[40.5,17.1],[41.7,19.4],[41.7,19.5],[46.3,38.8],[46.5,38.7],[46.7,41.0],[47.4,36.4],[47.4,36.6],[47.5,36.4],[47.5,36.6],[48.4,40.3],[48.4,40.5],[48.5,40.3],[48.5,40.5],[50.4,54.2],[50.5,54.2],[50.8,40.5],[51.0,40.3],[52.4,42.0],[52.4,53.8],[52.5,42.0],[52.5,53.8],[52.8,56.8],[53.3,44.4],[53.3,44.5],[53.3,58.8],[53.5,44.4],[53.5,44.5],[53.5,58.8],[54.8,41.5],[54.9,41.3],[55.6,80.0],[55.7,83.7],[55.8,75.8],[56.4,81.2],[56.5,81.2],[56.8,77.7],[56.9,77.4],[57.1,79.1],[57.2,79.5],[57.4,85.2],[57.4,85.5],[57.5,85.3],[57.6,85.5],[58.2,81.9],[58.4,76.8],[58.5,76.9],[60.1,79.0],[60.2,74.4],[60.2,74.5],[60.2,76.2],[60.3,76.5],[64.0,11.2],[65.3,23.5],[65.4,25.6],[65.5,21.0],[65.9,24.1],[66.4,26.5],[66.5,26.5],[66.8,24.6],[67.9,22.8],[68.0,20.2],[68.0,21.2]],"level":0,"name":"Azshara's Veil","type":2,"id":202749}]},"vein":{"Obsidium Deposit":[{"coords":[[35.2,22.1],[36.0,21.4],[36.1,21.5],[37.5,20.5],[38.2,19.6],[38.3,19.4],[46.7,23.9],[47.0,27.0],[48.3,19.4],[48.3,19.5],[48.5,19.3],[48.5,19.5],[48.7,33.0],[49.8,34.3],[49.8,34.5],[49.8,55.3],[49.8,55.5],[50.0,23.4],[50.1,23.6],[51.1,58.6],[51.2,58.4],[51.4,32.0],[51.4,36.0],[51.6,32.1],[51.6,36.0],[52.0,22.4],[52.1,22.7],[52.1,25.4],[52.1,25.5],[53.7,62.1],[53.9,25.2],[54.4,44.1],[54.4,64.0],[54.5,44.1],[54.5,64.0],[54.6,84.2],[54.9,27.4],[54.9,27.5],[56.3,46.2],[56.4,86.0],[56.5,46.2],[56.5,86.0],[57.9,87.9],[58.1,73.4],[58.1,73.6],[58.4,80.0],[58.5,80.0],[58.7,60.0],[58.7,76.8],[58.7,85.2],[59.1,46.9],[59.9,55.3],[59.9,55.5],[60.2,78.9],[61.0,45.2],[61.0,45.5],[61.9,57.4],[61.9,57.5],[62.4,59.4],[62.4,59.5],[62.6,59.4],[62.6,59.5],[64.8,25.8],[76.7,37.5]],"level":0,"name":"Obsidium Deposit","type":2,"id":202736}]},"skinnable":[39913,39948,39964,40219,40223,40276,40309,40466,40685,40855,41002,41997],"gatherable":[],"minable":[],"salvegable":[]}